CHANGES.txt
README.txt
bootstrap.py
buildout.cfg
setup.py
src/z3c/__init__.py
src/z3c.feature.zope.egg-info/PKG-INFO
src/z3c.feature.zope.egg-info/SOURCES.txt
src/z3c.feature.zope.egg-info/dependency_links.txt
src/z3c.feature.zope.egg-info/entry_points.txt
src/z3c.feature.zope.egg-info/namespace_packages.txt
src/z3c.feature.zope.egg-info/not-zip-safe
src/z3c.feature.zope.egg-info/requires.txt
src/z3c.feature.zope.egg-info/top_level.txt
src/z3c/feature/__init__.py
src/z3c/feature/zope/README.txt
src/z3c/feature/zope/__init__.py
src/z3c/feature/zope/browser.py
src/z3c/feature/zope/content.py
src/z3c/feature/zope/content.txt
src/z3c/feature/zope/index.txt
src/z3c/feature/zope/interfaces.py
src/z3c/feature/zope/project.py
src/z3c/feature/zope/skin.py
src/z3c/feature/zope/template.py
src/z3c/feature/zope/tests.py
src/z3c/feature/zope/zope-project.xml
src/z3c/feature/zope/file-templates/simple-page.pt
src/z3c/feature/zope/web/__init__.py
src/z3c/feature/zope/web/content.py
src/z3c/feature/zope/web/page.py
src/z3c/feature/zope/web/project.py